<?xml version="1.0" ?>
<annotation>
    <filename>2002/08/23/big/img_528</filename>
    <object>
        <face>face</face>
        <bndbox>
            <xmin>38</xmin>
            <ymin>130</ymin>
            <xmax>109</xmax>
            <ymax>239</ymax>
        </bndbox>
    </object>
    <object>
        <face>face</face>
        <bndbox>
            <xmin>82</xmin>
            <ymin>93</ymin>
            <xmax>104</xmax>
            <ymax>122</ymax>
        </bndbox>
    </object>
    <object>
        <face>face</face>
        <bndbox>
            <xmin>195</xmin>
            <ymin>100</ymin>
            <xmax>250</xmax>
            <ymax>177</ymax>
        </bndbox>
    </object>
    <object>
        <face>face</face>
        <bndbox>
            <xmin>375</xmin>
            <ymin>73</ymin>
            <xmax>440</xmax>
            <ymax>162</ymax>
        </bndbox>
    </object>
    <object>
        <face>face</face>
        <bndbox>
            <xmin>332</xmin>
            <ymin>89</ymin>
            <xmax>377</xmax>
            <ymax>155</ymax>
        </bndbox>
    </object>
    <object>
        <face>face</face>
        <bndbox>
            <xmin>357</xmin>
            <ymin>61</ymin>
            <xmax>382</xmax>
            <ymax>100</ymax>
        </bndbox>
    </object>
    <object>
        <face>face</face>
        <bndbox>
            <xmin>289</xmin>
            <ymin>69</ymin>
            <xmax>314</xmax>
            <ymax>101</ymax>
        </bndbox>
    </object>
</annotation>
