<?xml version="1.0" ?>
<annotation>
    <filename>2002/09/02/big/img_15586</filename>
    <object>
        <face>face</face>
        <bndbox>
            <xmin>80</xmin>
            <ymin>62</ymin>
            <xmax>160</xmax>
            <ymax>193</ymax>
        </bndbox>
    </object>
    <object>
        <face>face</face>
        <bndbox>
            <xmin>209</xmin>
            <ymin>98</ymin>
            <xmax>241</xmax>
            <ymax>143</ymax>
        </bndbox>
    </object>
    <object>
        <face>face</face>
        <bndbox>
            <xmin>139</xmin>
            <ymin>11</ymin>
            <xmax>160</xmax>
            <ymax>42</ymax>
        </bndbox>
    </object>
    <object>
        <face>face</face>
        <bndbox>
            <xmin>13</xmin>
            <ymin>55</ymin>
            <xmax>43</xmax>
            <ymax>98</ymax>
        </bndbox>
    </object>
    <object>
        <face>face</face>
        <bndbox>
            <xmin>244</xmin>
            <ymin>9</ymin>
            <xmax>277</xmax>
            <ymax>58</ymax>
        </bndbox>
    </object>
    <object>
        <face>face</face>
        <bndbox>
            <xmin>204</xmin>
            <ymin>21</ymin>
            <xmax>226</xmax>
            <ymax>51</ymax>
        </bndbox>
    </object>
    <object>
        <face>face</face>
        <bndbox>
            <xmin>203</xmin>
            <ymin>55</ymin>
            <xmax>230</xmax>
            <ymax>94</ymax>
        </bndbox>
    </object>
    <object>
        <face>face</face>
        <bndbox>
            <xmin>169</xmin>
            <ymin>43</ymin>
            <xmax>195</xmax>
            <ymax>79</ymax>
        </bndbox>
    </object>
</annotation>
