<?xml version="1.0" ?>
<annotation>
    <filename>2002/08/23/big/img_440</filename>
    <object>
        <face>face</face>
        <bndbox>
            <xmin>99</xmin>
            <ymin>43</ymin>
            <xmax>183</xmax>
            <ymax>172</ymax>
        </bndbox>
    </object>
    <object>
        <face>face</face>
        <bndbox>
            <xmin>196</xmin>
            <ymin>34</ymin>
            <xmax>282</xmax>
            <ymax>155</ymax>
        </bndbox>
    </object>
</annotation>
