<?xml version="1.0" ?>
<annotation>
    <filename>2002/08/06/big/img_2378</filename>
    <object>
        <face>face</face>
        <bndbox>
            <xmin>123</xmin>
            <ymin>51</ymin>
            <xmax>199</xmax>
            <ymax>148</ymax>
        </bndbox>
    </object>
    <object>
        <face>face</face>
        <bndbox>
            <xmin>333</xmin>
            <ymin>59</ymin>
            <xmax>404</xmax>
            <ymax>166</ymax>
        </bndbox>
    </object>
    <object>
        <face>face</face>
        <bndbox>
            <xmin>394</xmin>
            <ymin>123</ymin>
            <xmax>452</xmax>
            <ymax>207</ymax>
        </bndbox>
    </object>
</annotation>
