<?xml version="1.0" ?>
<annotation>
    <filename>2002/08/14/big/img_1071</filename>
    <object>
        <face>face</face>
        <bndbox>
            <xmin>90</xmin>
            <ymin>79</ymin>
            <xmax>196</xmax>
            <ymax>246</ymax>
        </bndbox>
    </object>
    <object>
        <face>face</face>
        <bndbox>
            <xmin>238</xmin>
            <ymin>-36</ymin>
            <xmax>304</xmax>
            <ymax>66</ymax>
        </bndbox>
    </object>
</annotation>
