<?xml version="1.0" ?>
<annotation>
    <filename>2002/08/29/big/img_19038</filename>
    <object>
        <face>face</face>
        <bndbox>
            <xmin>97</xmin>
            <ymin>23</ymin>
            <xmax>183</xmax>
            <ymax>141</ymax>
        </bndbox>
    </object>
    <object>
        <face>face</face>
        <bndbox>
            <xmin>259</xmin>
            <ymin>131</ymin>
            <xmax>304</xmax>
            <ymax>197</ymax>
        </bndbox>
    </object>
    <object>
        <face>face</face>
        <bndbox>
            <xmin>324</xmin>
            <ymin>64</ymin>
            <xmax>398</xmax>
            <ymax>188</ymax>
        </bndbox>
    </object>
</annotation>
